[
  {
    "Aliases": "CNAM",
    "Description": "Form Key or Editor ID",
    "Example": "\"Color\": \"123:Skyrim.esm\" or \"Color\": \"MyEditorID\"",
    "Flags": 28,
    "Name": "Color"
  },
  {
    "Aliases": "EDID",
    "Description": "String value",
    "Example": "\"EditorID\": \"Hello\"",
    "Flags": 28,
    "Name": "EditorID"
  },
  {
    "Aliases": "HNAM",
    "Description": "Form Keys or Editor IDs",
    "Example": "\"ExtraParts\": [ \"123:Skyrim.esm\", \"MyEditorID\" ]",
    "Flags": 124,
    "Name": "ExtraParts"
  },
  {
    "Aliases": "DATA",
    "Description": "Flags (Playable, Male, Female, IsExtraPart, UseSolidTint)",
    "Example": "\"Flags\": [ \"Playable\", \"-UseSolidTint\" ]",
    "Flags": 92,
    "Name": "Flags"
  },
  {
    "Aliases": "",
    "Description": "Numeric value",
    "Example": "\"FormVersion\": 7",
    "Flags": 30,
    "Name": "FormVersion"
  },
  {
    "Aliases": "",
    "Description": "True / False",
    "Example": "\"IsCompressed\": true",
    "Flags": 30,
    "Name": "IsCompressed"
  },
  {
    "Aliases": "",
    "Description": "True / False",
    "Example": "\"IsDeleted\": true",
    "Flags": 30,
    "Name": "IsDeleted"
  },
  {
    "Aliases": "RecordFlags",
    "Description": "Flags (NonPlayable)",
    "Example": "\"MajorFlags\": \"NonPlayable\"",
    "Flags": 92,
    "Name": "MajorFlags"
  },
  {
    "Aliases": "",
    "Description": "Numeric value",
    "Example": "\"MajorRecordFlagsRaw\": 7",
    "Flags": 30,
    "Name": "MajorRecordFlagsRaw"
  },
  {
    "Aliases": "",
    "Description": "Forward Model data.",
    "Example": "[{ \"types\": [\"Book\"], \"Forward\": { \"SomeMod.esp\": [\"Model\"] } }]",
    "Flags": 16,
    "Name": "Model"
  },
  {
    "Aliases": "",
    "Description": "Memory slice in form of array of bytes",
    "Example": "\"Model.Data\": [0x1A,0x00,0x3F]",
    "Flags": 25,
    "Name": "Model.Data"
  },
  {
    "Aliases": "FULL",
    "Description": "String value",
    "Example": "\"Name\": \"Hello\"",
    "Flags": 28,
    "Name": "Name"
  },
  {
    "Aliases": "",
    "Description": "",
    "Example": "",
    "Flags": 144,
    "Name": "Parts"
  },
  {
    "Aliases": "",
    "Description": "Flags (ESM, NotPlayable, Deleted, InitiallyDisabled, Ignored, VisibleWhenDistant, Dangerous_OffLimits_InteriorCell, Compressed, CantWait)",
    "Example": "\"SkyrimMajorRecordFlags\": [ \"ESM\", \"-CantWait\" ]",
    "Flags": 92,
    "Name": "SkyrimMajorRecordFlags"
  },
  {
    "Aliases": "TNAM",
    "Description": "Form Key or Editor ID",
    "Example": "\"TextureSet\": \"123:Skyrim.esm\" or \"TextureSet\": \"MyEditorID\"",
    "Flags": 28,
    "Name": "TextureSet"
  },
  {
    "Aliases": "PNAM",
    "Description": "Possible values (Misc, Face, Eyes, Hair, FacialHair, Scars, Eyebrows)",
    "Example": "\"Type\": \"Misc\"",
    "Flags": 12,
    "Name": "Type"
  },
  {
    "Aliases": "RNAM",
    "Description": "Form Key or Editor ID",
    "Example": "\"ValidRaces\": \"123:Skyrim.esm\" or \"ValidRaces\": \"MyEditorID\"",
    "Flags": 28,
    "Name": "ValidRaces"
  },
  {
    "Aliases": "",
    "Description": "Numeric value",
    "Example": "\"Version2\": 7",
    "Flags": 30,
    "Name": "Version2"
  },
  {
    "Aliases": "",
    "Description": "Numeric value",
    "Example": "\"VersionControl\": 7",
    "Flags": 30,
    "Name": "VersionControl"
  }
]