[
  {
    "Aliases": "",
    "Description": "",
    "Example": "",
    "Flags": 24,
    "Name": "CameraOffset"
  },
  {
    "Aliases": "",
    "Description": "String value",
    "Example": "\"EditorID\": \"Hello\"",
    "Flags": 28,
    "Name": "EditorID"
  },
  {
    "Aliases": "",
    "Description": "Flags (ESM, NotPlayable, Deleted, InitiallyDisabled, Ignored, VisibleWhenDistant, Dangerous_OffLimits_InteriorCell, Compressed, CantWait)",
    "Example": "\"Fallout4MajorRecordFlags\": [ \"ESM\", \"-CantWait\" ]",
    "Flags": 92,
    "Name": "Fallout4MajorRecordFlags"
  },
  {
    "Aliases": "",
    "Description": "Numeric value",
    "Example": "\"FormVersion\": 7",
    "Flags": 28,
    "Name": "FormVersion"
  },
  {
    "Aliases": "",
    "Description": "Decimal value",
    "Example": "\"FovMult\": 3.14",
    "Flags": 28,
    "Name": "FovMult"
  },
  {
    "Aliases": "",
    "Description": "Form Key or Editor ID",
    "Example": "",
    "Flags": 28,
    "Name": "ImagespaceModifier"
  },
  {
    "Aliases": "",
    "Description": "True / False",
    "Example": "\"IsCompressed\": true",
    "Flags": 28,
    "Name": "IsCompressed"
  },
  {
    "Aliases": "",
    "Description": "True / False",
    "Example": "\"IsDeleted\": true",
    "Flags": 28,
    "Name": "IsDeleted"
  },
  {
    "Aliases": "",
    "Description": "Numeric value",
    "Example": "\"MajorRecordFlagsRaw\": 7",
    "Flags": 28,
    "Name": "MajorRecordFlagsRaw"
  },
  {
    "Aliases": "",
    "Description": "Possible values (Default, Fine, Duplex, German, Dot, MilDot, Circle, OldRangefind, ModernRangefind, SVD, HandPainted, Binoculars, Cross, DoubleZero, Rangefinder1, Rangefinder2, Rectangle)",
    "Example": "\"Overlay\": \"Default\"",
    "Flags": 12,
    "Name": "Overlay"
  },
  {
    "Aliases": "",
    "Description": "Numeric value",
    "Example": "\"Version2\": 7",
    "Flags": 28,
    "Name": "Version2"
  },
  {
    "Aliases": "",
    "Description": "Numeric value",
    "Example": "\"VersionControl\": 7",
    "Flags": 28,
    "Name": "VersionControl"
  }
]